.editorconfig
.gitignore
.gitlab-ci.yml
README.rst
publish.settings.sh
publish.sh
pyproject.toml
tsconfig.json
.idea/modules.xml
.idea/peek-plugin-branch.iml
.idea/inspectionProfiles/Project_Default.xml
.idea/inspectionProfiles/profiles_settings.xml
peek_plugin_branch/__init__.py
peek_plugin_branch/plugin_package.json
peek_plugin_branch.egg-info/PKG-INFO
peek_plugin_branch.egg-info/SOURCES.txt
peek_plugin_branch.egg-info/dependency_links.txt
peek_plugin_branch.egg-info/requires.txt
peek_plugin_branch.egg-info/top_level.txt
peek_plugin_branch/_private/PluginNames.py
peek_plugin_branch/_private/__init__.py
peek_plugin_branch/_private/alembic.ini
peek_plugin_branch/_private/admin-app/branch.module.ts
peek_plugin_branch/_private/admin-app/components/branch-page/branch-page.component.html
peek_plugin_branch/_private/admin-app/components/branch-page/branch-page.component.scss
peek_plugin_branch/_private/admin-app/components/branch-page/branch-page.component.ts
peek_plugin_branch/_private/admin-app/components/edit-branch-detail-table/edit.component.html
peek_plugin_branch/_private/admin-app/components/edit-branch-detail-table/edit.component.scss
peek_plugin_branch/_private/admin-app/components/edit-branch-detail-table/edit.component.ts
peek_plugin_branch/_private/admin-app/components/edit-setting-table/edit.component.html
peek_plugin_branch/_private/admin-app/components/edit-setting-table/edit.component.scss
peek_plugin_branch/_private/admin-app/components/edit-setting-table/edit.component.ts
peek_plugin_branch/_private/alembic/__init__.py
peek_plugin_branch/_private/alembic/env.py
peek_plugin_branch/_private/alembic/script.py.mako
peek_plugin_branch/_private/alembic/versions/53e411bea4ab_initial_tables.py
peek_plugin_branch/_private/alembic/versions/87f770b6a183_removed_location_field.py
peek_plugin_branch/_private/alembic/versions/__init__.py
peek_plugin_branch/_private/both-app/branch.component.dweb.html
peek_plugin_branch/_private/both-app/branch.component.mweb.html
peek_plugin_branch/_private/both-app/branch.component.ts
peek_plugin_branch/_private/both-app/branch.module.ts
peek_plugin_branch/_private/both-app/branch-detail/branch-detail.component.dweb.html
