Metadata-Version: 2.4
Name: peek-plugin-branch
Version: 5.0.4
Summary: Peek Plugin Branch - provides branch detail objects for Peek plugins
Author-email: Synerty <contact@synerty.com>
Project-URL: Homepage, https://github.com/Synerty/peek-plugin-branch
Keywords: Peek,Python,Platform,synerty
Requires-Dist: peek-plugin-base==5.0.4
